[
  { "id": "slime", "name": "Slime", "hp": 5, "moveSpeed": 60, "damage": 5, "soulValue": 1, "flag": "ground", "tintColor": "0x4ade80" },
  { "id": "skeleton", "name": "Skeleton", "hp": 12, "moveSpeed": 80, "damage": 8, "soulValue": 2, "flag": "ground", "tintColor": "0xd1d5db" },
  { "id": "ghost", "name": "Ghost", "hp": 10, "moveSpeed": 70, "damage": 6, "soulValue": 2, "flag": "phasing", "tintColor": "0xc4b5fd", "alpha": 0.7, "meleeDodgeChance": 0.4 },
  { "id": "orc", "name": "Orc", "hp": 35, "moveSpeed": 50, "damage": 12, "soulValue": 3, "flag": "ground", "tintColor": "0x7f1d1d" },
  { "id": "bat", "name": "Bat", "hp": 6, "moveSpeed": 140, "damage": 4, "soulValue": 1, "flag": "flying", "tintColor": "0xfbbf24", "movementPattern": "zigzag" }
]
